typer_cmd-0.0.2.dist-info/METADATA
typer_cmd-0.0.2.dist-info/WHEEL
typer_cmd-0.0.2.dist-info/licenses/LICENSE
typer_cmd/__init__.py
typer_cmd/shell.py
typer_cmd-0.0.2.dist-info/RECORD
