Metadata-Version: 2.1
Name: typer-cmd
Version: 0.0.2
Summary: An extension to typer that easily turns your typer app into a shell utility
Author-Email: tanglh <tlhk2@163.com>
License: MIT
Requires-Python: >=3.9
Requires-Dist: typer>=0.9.0
Requires-Dist: pyreadline3>=3.4.1
Requires-Dist: rich>=13.6.0
